JAVA_CLASS_GENERATOR/java_class_generator.py
JAVA_CLASS_GENERATOR-1.dist-info/LICENSE
JAVA_CLASS_GENERATOR-1.dist-info/METADATA
JAVA_CLASS_GENERATOR-1.dist-info/WHEEL
JAVA_CLASS_GENERATOR-1.dist-info/entry_points.txt
JAVA_CLASS_GENERATOR-1.dist-info/top_level.txt
JAVA_CLASS_GENERATOR-1.dist-info/RECORD
