Metadata-Version: 2.1
Name: JAVA-CLASS-GENERATOR
Version: 1
Summary: This package contains implementation of the application "Java Class Generator". This application allows users to reduce the effort needed to write Java classes.
Home-page: https://github.com/DigitalCreativeApkDev/JAVA_CLASS_GENERATOR
Author: DigitalCreativeApkDev
Author-email: digitalcreativeapkdev2022@gmail.com
License: MIT
Platform: UNKNOWN
Classifier: Programming Language :: Python :: 3
Classifier: Programming Language :: Python :: 3.7
